0110_sequence_detector.v/0110_seq_detector.v
module seq_dec(clock, x, z);

input clock, x;

output reg z;

reg [0:2] state;

parameter s0=1'b1, s1=1'b0, s2=2'b01, s3=3'b011;

always @ (posedge clock)

 case (state)
   
   s0: state<=x ? s0 : s1;
   s1 : state<=x ? s2 :s1;
   s2 : state<=x ? s3:s1;
   s3 : state<=x ? s0:s1;
   
   

   default : state<=s0;

  

   endcase

always @(state)
 
 case (state)
   
   s3 : z= x ? 0:1;

   default: z=0;

   endcase
  

  endmodule


  /// testbench

  module testbench;

  reg clk, x;

  output z;

  seq_dec s1 (clk, x, z);

  initial 

  begin
   clk=1'b0;
   x=0;
   
   end
   always #5 clk=~clk;


   initial
    begin
       #12 x=1'b0; 
       #10 x=0;
       #10 x=1;
       #10 x=1;
       #10 x=0;
       #10 x=0;
       #10 x=1;
        
      
    end
   
 initial 

  begin
    
    $monitor ($time, "x=%b, z=%b,clk=%b", x,z,clk);
    $dumpfile ("0110.vcd");
    $dumpvars (0,testbench);
    #105
     $finish;
  end
   
   endmodule

0110_sequence_detector.v/0110.vcd
$date
	Mon Mar 22 21:00:12 2021
$end
$version
	Icarus Verilog
$end
$timescale
	1s
$end
$scope module testbench $end
$var wire 1 ! z $end
$var reg 1 " clk $end
$var reg 1 # x $end
$scope module s1 $end
$var wire 1 " clock $end
$var wire 1 # x $end
$var reg 3 $ state [0:2] $end
$var reg 1 ! z $end
$upscope $end
$upscope $end
$enddefinitions $end
#0
$dumpvars
bx $
0#
0"
x!
$end
#5
0!
b1 $
1"
#10
0"
#15
b0 $
1"
#20
0"
#25
1"
#30
0"
#32
1#
#35
b1 $
1"
#40
0"
#45
1"
#50
0"
#52
0#
#55
b0 $
1"
#60
0"
#65
1"
#70
0"
#72
1#
#75
b1 $
1"
